{"cookies": [{"name": "session_token", "value": "fake_auth_token", "domain": "the-internet.herokuapp.com", "path": "/", "expires": -1, "httpOnly": false, "secure": false, "sameSite": "Lax"}, {"name": "rack.session", "value": "BAh7CUkiD3Nlc3Npb25faWQGOgZFVEkiRTUzM2QzZDI3YzM1OTFkM2IxNmI1%0ANmY1NGJiZDRlMjE0NmI0ZjlmYzVkODMzMjY0NDA1ZGY4ZDJhYWJhOTQwNjgG%0AOwBGSSIJY3NyZgY7AEZJIiUzYjk2MjRlZDRiYjkzZGE4ODg1MTc4ZWFkNWYw%0AYzA0YQY7AEZJIg10cmFja2luZwY7AEZ7B0kiFEhUVFBfVVNFUl9BR0VOVAY7%0AAFRJIi1hZGUzNDE0YTNmZDQ4Njc4YmJkOWYwMTE0ODAyNTI4MjY2OTJiYWYz%0ABjsARkkiGUhUVFBfQUNDRVBUX0xBTkdVQUdFBjsAVEkiLWQ0ZTdkMzNmNGVi%0ANzNiY2U4ZmY3MDdjODBiNjlhYzU3ZWU1YzlmYmMGOwBGSSIKZmxhc2gGOwBG%0AewA%3D%0A--1ce1ef9750e35249e6ce0bf78e929d55b19abec2", "domain": "the-internet.herokuapp.com", "path": "/", "expires": -1, "httpOnly": true, "secure": false, "sameSite": "Lax"}, {"name": "optimizelySegments", "value": "%7B%7D", "domain": ".the-internet.herokuapp.com", "path": "/", "expires": 1815794047.826134, "httpOnly": false, "secure": false, "sameSite": "Lax"}, {"name": "optimizelyEndUserId", "value": "oeu1781234047828r0.7133098238938499", "domain": ".the-internet.herokuapp.com", "path": "/", "expires": 1815794047.829995, "httpOnly": false, "secure": false, "sameSite": "Lax"}, {"name": "optimizelyBuckets", "value": "%7B%7D", "domain": ".the-internet.herokuapp.com", "path": "/", "expires": 1815794047.833035, "httpOnly": false, "secure": false, "sameSite": "Lax"}, {"name": "optimizelyPendingLogEvents", "value": "%5B%22n%3Dhttps%253A%252F%252Fthe-internet.herokuapp.com%252F%26u%3Doeu1781234047828r0.7133098238938499%26wxhr%3Dtrue%26t%3D1781234047836%26f%3D298349752%2C318188263%22%5D", "domain": ".the-internet.herokuapp.com", "path": "/", "expires": 1781234062, "httpOnly": false, "secure": false, "sameSite": "Lax"}], "origins": []}